tests/counter_value_in_while_waiting_in_start.v
`timescale 1ns/1ps

module CounterValue
#(
    parameter WAIT_NUMBER = 234
)
(
    input clk, uart_rx
);
    reg[1:0] state; // 0 in idle, 1 in start, 2 in other just for debugging
    reg[7:0] counter;

    always @(posedge clk) begin
        case (state)
            0: // meaning idle
            begin
                if (uart_rx == 1'b0) begin
                    counter <= 1;
                    state <= 1; // move to start
                end
            end
            1: // meaning start
            begin
                counter <= counter + 1;
                if (counter == WAIT_NUMBER) begin
                    counter <= 0;
                    state <= 2; // for debugging done waiting
                end
            end
            2: begin
                counter <= 0; //stuck at state 2s
            end
            default:
                state <= 0;
        endcase
    end

endmodule

module CounterValue_tb;

reg clk = 0;
reg uart_rx = 1;

CounterValue #(.WAIT_NUMBER(8)) uut0
(
    .clk(clk), .uart_rx(uart_rx)
);

always #1 clk = ~clk;

initial begin
    $dumpfile("counter_value_in_while_waiting_in_start.vcd");
    $dumpvars;
    #5; // so default case is executed and and now shoud be idle

    uart_rx = 0; // now we should start

    #1000 $finish;

end

endmodule

tests/counter_value_in_while_waiting_in_start.vcd
$date
	Mon Aug 19 11:12:06 2024
$end
$version
	Icarus Verilog
$end
$timescale
	1ps
$end
$scope module CounterValue_tb $end
$var reg 1 ! clk $end
$var reg 1 " uart_rx $end
$scope module uut0 $end
$var wire 1 ! clk $end
$var wire 1 " uart_rx $end
$var parameter 32 # WAIT_NUMBER $end
$var reg 8 $ counter [7:0] $end
$var reg 2 % state [1:0] $end
$upscope $end
$upscope $end
$enddefinitions $end
$comment Show the parameter values. $end
$dumpall
b1000 #
$end
#0
$dumpvars
bx %
bx $
1"
0!
$end
#1000
b0 %
1!
#2000
0!
#3000
1!
#4000
0!
#5000
b1 %
b1 $
1!
0"
#6000
0!
#7000
b10 $
1!
#8000
0!
#9000
b11 $
1!
#10000
0!
#11000
b100 $
1!
#12000
0!
#13000
b101 $
1!
#14000
0!
#15000
b110 $
1!
#16000
0!
#17000
b111 $
1!
#18000
0!
#19000
b1000 $
1!
#20000
0!
#21000
b10 %
b0 $
1!
